legisph/__init__.py
legisph/core/__init__.py
legisph/core/logging.py
legisph/core/models.py
legisph/core/website.py
legisph/senate/__init__.py
legisph/senate/models.py
legisph/senate/website.py
legisph-0.3.0.dist-info/METADATA
legisph-0.3.0.dist-info/WHEEL
legisph-0.3.0.dist-info/RECORD
