Metadata-Version: 2.1
Name: legisph
Version: 0.3.0
Summary: Legislative Analysis of the Philippines
License: CC BY-NC-ND 4.0
Author: TJ Palanca
Author-email: mail@tjpalanca.com
Requires-Python: >=3.11,<4.0
Classifier: License :: Other/Proprietary License
Classifier: Programming Language :: Python :: 3
Classifier: Programming Language :: Python :: 3.11
Requires-Dist: beautifulsoup4 (>=4.12.2,<5.0.0)
Requires-Dist: diskcache (>=5.6.3,<6.0.0)
Requires-Dist: html5lib (>=1.1,<2.0)
Requires-Dist: logging (>=0.4.9.6,<0.5.0.0)
Requires-Dist: more-itertools (>=10.1.0,<11.0.0)
Requires-Dist: pydantic (>=2.4.2,<3.0.0)
Requires-Dist: requests (>=2.31.0,<3.0.0)
Requires-Dist: requests-cache (>=1.1.0,<2.0.0)
Requires-Dist: rich (>=13.6.0,<14.0.0)
